pakk/__init__.py
pakk-2.1.0.data/scripts/pakk
pakk-2.1.0.dist-info/METADATA
pakk-2.1.0.dist-info/RECORD
pakk-2.1.0.dist-info/WHEEL
pakk-2.1.0.dist-info/top_level.txt
